LICENSE.txt
MANIFEST.in
README.rst
setup.cfg
setup.py
affiliations/__init__.py
affiliations/admin.py
affiliations/affiliations_settings.py
affiliations/apps.py
affiliations/exceptions.py
affiliations/middleware.py
affiliations/models.py
affiliations/triggers.py
affiliations/utils.py
affiliations/migrations/0001_initial.py
affiliations/migrations/__init__.py
affiliations/tests/__init__.py
affiliations/tests/test_affiliations_settings.py
affiliations/tests/test_apps.py
affiliations/tests/test_middleware.py
affiliations/tests/test_models.py
affiliations/tests/test_triggers.py
affiliations/tests/test_utils.py
affiliations/tests/utils.py
django_affiliate_tracking.egg-info/PKG-INFO
django_affiliate_tracking.egg-info/SOURCES.txt
django_affiliate_tracking.egg-info/dependency_links.txt
django_affiliate_tracking.egg-info/not-zip-safe
django_affiliate_tracking.egg-info/requires.txt
django_affiliate_tracking.egg-info/top_level.txt