Metadata-Version: 1.1
Name: django-affiliate-tracking
Version: 0.12
Summary: A Django app providing mechanisms to track users and actions, to know when certain conditions are met.
Home-page: https://saxo.githost.io/publish/django-affiliate-tracking/
Author: Saxo Publish
Author-email: publish@saxo.com
License: BSD License 2.0
Keywords: django,affiliations
Platform: UNKNOWN
Classifier: Framework :: Django
Classifier: Intended Audience :: Developers
Classifier: Programming Language :: Python :: 2
Classifier: Programming Language :: Python :: 3
